locust_cloud/__init__.py
locust_cloud/apisession.py
locust_cloud/args.py
locust_cloud/common.py
locust_cloud/import_finder.py
locust_cloud/input_events.py
locust_cloud/web_login.py
locust_cloud/websocket.py
locust_cloud/docs/.gitignore
locust_cloud/docs/1-first-run.rst
locust_cloud/docs/2-examples.rst
locust_cloud/docs/docs.rst
locust_cloud/docs/kubernetes-operator.rst
locust_cloud/docs/locust-cloud.rst
locust_cloud/docs/images/locust-cloud-screenshot.png
locust_cloud-1.28.0.dist-info/METADATA
locust_cloud-1.28.0.dist-info/WHEEL
locust_cloud-1.28.0.dist-info/licenses/LICENSE
locust_cloud-1.28.0.dist-info/RECORD
