Metadata-Version: 2.4
Name: locust-cloud
Version: 1.28.0
Summary: Locust Cloud
Project-URL: homepage, https://locust.cloud
Project-URL: repository, https://github.com/locustcloud/locust-cloud
License: MIT
License-File: LICENSE
Requires-Python: >=3.10
Requires-Dist: configargparse>=1.7.1
Requires-Dist: gevent<26.0.0,>=24.10.1
Requires-Dist: platformdirs<5.0.0,>=4.3.6
Requires-Dist: python-engineio>=4.12.2
Requires-Dist: python-socketio[client]<6.0.0,>=5.14.1
Requires-Dist: tomli>=1.1.0; python_version < '3.11'
